flask_remote_logging/__init__.py
flask_remote_logging/aws_extension.py
flask_remote_logging/azure_extension.py
flask_remote_logging/base_extension.py
flask_remote_logging/compat.py
flask_remote_logging/context_filter.py
flask_remote_logging/extension.py
flask_remote_logging/gcp_extension.py
flask_remote_logging/ibm_extension.py
flask_remote_logging/middleware.py
flask_remote_logging/oci_extension.py
flask_remote_logging-1.1.3.dist-info/licenses/LICENSE
flask_remote_logging-1.1.3.dist-info/METADATA
flask_remote_logging-1.1.3.dist-info/WHEEL
flask_remote_logging-1.1.3.dist-info/top_level.txt
flask_remote_logging-1.1.3.dist-info/RECORD
