Metadata-Version: 2.4
Name: flask-remote-logging
Version: 1.1.3
Summary: Flask extension for sending logs to remote logging services including Graylog, Google Cloud Logging, AWS CloudWatch Logs, and Azure Monitor Logs.
Author-email: Marc Ford <thenixninja@gmail.com>
Maintainer-email: Marc Ford <thenixninja@gmail.com>
License: MIT
Project-URL: Homepage, https://github.com/MarcFord/flask-remote-logging
Project-URL: Bug Reports, https://github.com/MarcFord/flask-remote-logging/issues
Project-URL: Source, https://github.com/MarcFord/flask-remote-logging
Project-URL: Documentation, https://github.com/MarcFord/flask-remote-logging#readme
Project-URL: Changelog, https://github.com/MarcFord/flask-remote-logging/blob/main/CHANGELOG.md
Keywords: flask,graylog,gelf,logging,extension,google-cloud-logging,gcp,aws,cloudwatch,azure,monitor,remote-logging
Classifier: Development Status :: 4 - Beta
Classifier: Intended Audience :: Developers
Classifier: Operating System :: OS Independent
Classifier: Programming Language :: Python :: 3.9
Classifier: Programming Language :: Python :: 3.10
Classifier: Programming Language :: Python :: 3.11
Classifier: Programming Language :: Python :: 3.12
Classifier: Framework :: Flask
Classifier: Topic :: Software Development :: Libraries :: Python Modules
Classifier: Topic :: System :: Networking
Classifier: Topic :: Communications
Requires-Python: >=3.9
License-File: LICENSE
Requires-Dist: flask<3.0.0,>=1.1.4
Requires-Dist: user-agents>=2.0.0
Provides-Extra: graylog
Requires-Dist: pygelf>=0.4.2; extra == "graylog"
Provides-Extra: gcp
Requires-Dist: google-cloud-logging>=3.0.0; extra == "gcp"
Provides-Extra: aws
Requires-Dist: boto3>=1.26.0; extra == "aws"
Provides-Extra: azure
Requires-Dist: requests>=2.25.0; extra == "azure"
Provides-Extra: ibm
Requires-Dist: requests>=2.25.0; extra == "ibm"
Provides-Extra: oci
Requires-Dist: oci>=2.40.0; extra == "oci"
Provides-Extra: all
Requires-Dist: pygelf>=0.4.2; extra == "all"
Requires-Dist: google-cloud-logging>=3.0.0; extra == "all"
Requires-Dist: boto3>=1.26.0; extra == "all"
Requires-Dist: requests>=2.25.0; extra == "all"
Requires-Dist: oci>=2.40.0; extra == "all"
Provides-Extra: test
Requires-Dist: pytest>=6.0; extra == "test"
Requires-Dist: pytest-cov<6.0,>=2.10; extra == "test"
Requires-Dist: pytest-mock<4.0,>=3.6; extra == "test"
Requires-Dist: pytest-xdist<4.0,>=2.0; extra == "test"
Provides-Extra: dev
Requires-Dist: isort>=5.0; extra == "dev"
Requires-Dist: mypy>=1.0; extra == "dev"
Requires-Dist: bandit>=1.7.0; extra == "dev"
Requires-Dist: flake8>=4.0; extra == "dev"
Requires-Dist: pre-commit>=2.20.0; extra == "dev"
Provides-Extra: docs
Requires-Dist: sphinx>=5.0.0; extra == "docs"
Requires-Dist: myst-parser>=1.0.0; extra == "docs"
Dynamic: license-file
